pubmed_search/__init__.py
pubmed_search/client.py
pubmed_search/py.typed
pubmed_search/session.py
pubmed_search/api/__init__.py
pubmed_search/api/server.py
pubmed_search/entrez/__init__.py
pubmed_search/entrez/base.py
pubmed_search/entrez/batch.py
pubmed_search/entrez/citation.py
pubmed_search/entrez/icite.py
pubmed_search/entrez/pdf.py
pubmed_search/entrez/search.py
pubmed_search/entrez/strategy.py
pubmed_search/entrez/utils.py
pubmed_search/exports/__init__.py
pubmed_search/exports/formats.py
pubmed_search/exports/links.py
pubmed_search/mcp/__init__.py
pubmed_search/mcp/__main__.py
pubmed_search/mcp/prompts.py
pubmed_search/mcp/server.py
pubmed_search/mcp/session_tools.py
pubmed_search/mcp/tools/__init__.py
pubmed_search/mcp/tools/_common.py
pubmed_search/mcp/tools/citation_tree.py
pubmed_search/mcp/tools/core.py
pubmed_search/mcp/tools/discovery.py
pubmed_search/mcp/tools/europe_pmc.py
pubmed_search/mcp/tools/export.py
pubmed_search/mcp/tools/merge.py
pubmed_search/mcp/tools/ncbi_extended.py
pubmed_search/mcp/tools/pico.py
pubmed_search/mcp/tools/strategy.py
pubmed_search/sources/__init__.py
pubmed_search/sources/core.py
pubmed_search/sources/europe_pmc.py
pubmed_search/sources/ncbi_extended.py
pubmed_search/sources/openalex.py
pubmed_search/sources/semantic_scholar.py
pubmed_search_mcp-0.1.18.dist-info/METADATA
pubmed_search_mcp-0.1.18.dist-info/WHEEL
pubmed_search_mcp-0.1.18.dist-info/entry_points.txt
pubmed_search_mcp-0.1.18.dist-info/licenses/LICENSE
pubmed_search_mcp-0.1.18.dist-info/RECORD
