Metadata-Version: 2.4
Name: pubmed-search-mcp
Version: 0.1.18
Summary: MCP server for PubMed literature search with MeSH, PICO, and intelligent query expansion
Project-URL: Homepage, https://github.com/u9401066/pubmed-search-mcp
Project-URL: Repository, https://github.com/u9401066/pubmed-search-mcp
Project-URL: Issues, https://github.com/u9401066/pubmed-search-mcp/issues
Author-email: Eric <u9401066@gmail.com>
License-Expression: Apache-2.0
License-File: LICENSE
Keywords: entrez,literature,mcp,medical,model-context-protocol,ncbi,pubmed,research,search
Classifier: Development Status :: 4 - Beta
Classifier: Intended Audience :: Developers
Classifier: Intended Audience :: Science/Research
Classifier: License :: OSI Approved :: Apache Software License
Classifier: Programming Language :: Python :: 3
Classifier: Programming Language :: Python :: 3.11
Classifier: Programming Language :: Python :: 3.12
Classifier: Programming Language :: Python :: 3.13
Classifier: Topic :: Scientific/Engineering :: Bio-Informatics
Classifier: Topic :: Scientific/Engineering :: Medical Science Apps.
Requires-Python: >=3.11
Requires-Dist: biopython>=1.81
Requires-Dist: mcp>=1.0.0
Requires-Dist: pylatexenc>=2.10
Requires-Dist: requests>=2.28.0
Provides-Extra: all
Requires-Dist: pytest-asyncio>=0.21; extra == 'all'
Requires-Dist: pytest>=7.0; extra == 'all'
Provides-Extra: dev
Requires-Dist: pytest-asyncio>=0.21; extra == 'dev'
Requires-Dist: pytest>=7.0; extra == 'dev'
